[
 {
  "table":"OBJH",
  "data":
  [
   {
    "OBJECTNAME":"DCLS",
    "OBJECTTYPE":"L",
    "CLIDEP":"",
    "LANGDEP":"X",
    "ALEDEP":"",
    "OBJCATEG":"SYST",
    "TRCOMPLETE":"",
    "TRDISJUNCT":"",
    "PHASELEVEL":0,
    "LOCKMETH":"",
    "TADIRCMETH":"",
    "CHECKID":"L",
    "OBJNAMELEN":40,
    "PROTECT":"",
    "OBJTRANSP":"2",
    "LUSER":"",
    "LDATE":"0000-00-00",
    "OBJNAMECLS":"1",
    "CURSETTING":"",
    "OBJHASADDR":"",
    "IMPORTABLE":"",
    "OBJCHARSET":"1",
    "MCCATEGORY":"",
    "MCDOCUID":"",
    "ABAP_LANGUAGE_VERSION":""
   }
  ]
 },
 {
  "table":"OBJM",
  "data":
  [
   {
    "OBJECTNAME":"DCLS",
    "OBJECTTYPE":"L",
    "METHOD":"AFTER_IMP",
    "METHODNAME":"SACMDT_AFTER_IMP_DCL",
    "UPGRADE":"X",
    "MULTI_OBJ":"",
    "LANG_OBJ":"",
    "SHADOW_SYS":"X"
   }
  ]
 },
 {
  "table":"OBJS",
  "data":
  [
   {
    "OBJECTNAME":"DCLS",
    "OBJECTTYPE":"L",
    "TABNAME":"ACMDCLSRC",
    "COVER":"",
    "CANDIDATE":"",
    "DDIC":"X",
    "PRIM_TABLE":"X",
    "VIEWGRANT":"",
    "TAB_FILLED":""
   },
   {
    "OBJECTNAME":"DCLS",
    "OBJECTTYPE":"L",
    "TABNAME":"ACMDCLSRCT",
    "COVER":"",
    "CANDIDATE":"",
    "DDIC":"X",
    "PRIM_TABLE":"",
    "VIEWGRANT":"",
    "TAB_FILLED":""
   }
  ]
 },
 {
  "table":"OBJSL",
  "data":
  [
   {
    "OBJECTNAME":"DCLS",
    "OBJECTTYPE":"L",
    "TRWCOUNT":1,
    "TPGMID":"R3TR",
    "TOBJECT":"TABU",
    "TOBJ_NAME":"ACMDCLSRC",
    "TOBJKEY":"/&A",
    "MASKNLEN":9,
    "MASKKLEN":2,
    "PRIM_TABLE":"X"
   },
   {
    "OBJECTNAME":"DCLS",
    "OBJECTTYPE":"L",
    "TRWCOUNT":2,
    "TPGMID":"R3TR",
    "TOBJECT":"TABU",
    "TOBJ_NAME":"ACMDCLSRCT",
    "TOBJKEY":"/&/LA",
    "MASKNLEN":10,
    "MASKKLEN":3,
    "PRIM_TABLE":""
   }
  ]
 },
 {
  "table":"OBJT",
  "data":
  [
   {
    "LANGUAGE":"E",
    "OBJECTNAME":"DCLS",
    "OBJECTTYPE":"L",
    "DDTEXT":"ABAP Data Control Language Sources"
   }
  ]
 }
]